game_package/__init__.py
game_package/main.py
game_package/other.modules.py
anurags_package-0.1.0.dist-info/METADATA
anurags_package-0.1.0.dist-info/WHEEL
anurags_package-0.1.0.dist-info/entry_points.txt
anurags_package-0.1.0.dist-info/top_level.txt
anurags_package-0.1.0.dist-info/RECORD
