Metadata-Version: 2.1
Name: anurags_package
Version: 0.1.0
Summary: A fun command-line game!
Home-page: https://github.com/anurag9601/own-package.git
Author: Anurag mishra
Classifier: Programming Language :: Python :: 3
Classifier: License :: OSI Approved :: MIT License
Classifier: Operating System :: OS Independent
Requires-Python: >=3.6
